Workbook

Sheet Grunddaten
A1: Grundaten zur Liquiditätsplanung
G2: Summe
E3: Kredit- | G3: Bank 1 | H3: Bank 2 | I3: Bank 3 | J3: Bank 4 | K3: Bank 5 | L3: Bank 6 | M3: Bank 7 | N3: Bank 8 | O3: gesamtes
E4: limit | O4: Kreditlimit
D5: Konto-Nr. | E5: T€ | G5: T€ | H5: T€ | I5: T€ | J5: T€ | K5: T€ | L5: T€ | M5: T€ | N5: T€ | O5: T€
A6: Standort 1
A8: 1. | B8: Bank 1 | E8: 550 | G8: =+E8 -> 550 | O8: =SUM(G8:N8) -> 550
A9: 2. | B9: Bank 2 | H9: =+E9 -> 0 | O9: =SUM(G9:N9) -> 0
A10: 3. | B10: Bank 3 | E10: 340.9 | I10: =+E10 -> 340.9 | O10: =SUM(G10:N10) -> 340.9
A11: 4. | B11: Bank 4 | E11: 227.3 | J11: =+E11 -> 227.3 | O11: =SUM(G11:N11) -> 227.3
A12: 5. | B12: Bank 5 | E12: 97.1 | K12: =+E12 -> 97.1 | O12: =SUM(G12:N12) -> 97.1
A13: 6. | B13: Bank 6 | L13: 0 | O13: =SUM(G13:N13) -> 0
A14: 7. | B14: Bank 7 | E14: 25.6 | M14: 25.6 | O14: =SUM(G14:N14) -> 25.6
A15: 8. | B15: Bank 8 | N15: 0 | O15: =SUM(G15:N15) -> 0
E16: =SUM(E8:E15) -> 1240.9 | G16: =SUM(G8:G15) -> 550 | H16: =SUM(H8:H15) -> 0 | I16: =SUM(I8:I15) -> 340.9 | J16: =SUM(J8:J15) -> 227.3 | K16: =SUM(K8:K15) -> 97.1 | L16: =SUM(L8:L15) -> 0 | M16: =SUM(M8:M15) -> 25.6 | N16: =SUM(N8:N15) -> 0 | O16: =SUM(O8:O15) -> 1240.9
A18: Standort 2
A20: 1. | B20: Bank 1 | E20: 0 | G20: =+E20 -> 0 | O20: =SUM(G20:N20) -> 0
A21: 2. | B21: Bank 2 | E21: 481.8 | H21: =+E21 -> 481.8 | O21: =SUM(G21:N21) -> 481.8
A22: 3. | B22: Bank 3 | I22: =+E22 -> 0 | O22: =SUM(G22:N22) -> 0
A23: 4. | B23: Bank 4 | J23: =+E23 -> 0 | O23: =SUM(G23:N23) -> 0
A24: 5. | B24: Bank 5 | E24: 0 | K24: =+E24 -> 0 | O24: =SUM(G24:N24) -> 0
A25: 6. | B25: Bank 6 | L25: 0 | O25: =SUM(G25:N25) -> 0
A26: 7. | B26: Bank 7 | M26: 0 | O26: =SUM(G26:N26) -> 0
A27: 8. | B27: Bank 8 | N27: 0 | O27: =SUM(G27:N27) -> 0
E28: =SUM(E20:E25) -> 481.8 | G28: =SUM(G20:G25) -> 0 | H28: =SUM(H20:H25) -> 481.8 | I28: =SUM(I20:I25) -> 0 | J28: =SUM(J20:J25) -> 0 | K28: =SUM(K20:K25) -> 0 | L28: =SUM(L20:L25) -> 0 | M28: =SUM(M20:M25) -> 0 | N28: =SUM(N20:N25) -> 0 | O28: =SUM(O20:O25) -> 481.8
A30: Standort 3
A32: 1. | B32: Bank 1 | E32: 50 | G32: =+E32 -> 50 | O32: =SUM(G32:N32) -> 50
A33: 2. | B33: Bank 2 | E33: 200 | H33: =+E33 -> 200 | O33: =SUM(G33:N33) -> 200
A34: 3. | B34: Bank 3 | I34: =+E34 -> 0 | O34: =SUM(G34:N34) -> 0
A35: 4. | B35: Bank 4 | J35: =+E35 -> 0 | O35: =SUM(G35:N35) -> 0
A36: 5. | B36: Bank 5 | E36: 0 | K36: =+E36 -> 0 | O36: =SUM(G36:N36) -> 0
A37: 6. | B37: Bank 6 | E37: 50 | L37: 50 | O37: =SUM(G37:N37) -> 50
A38: 7. | B38: Bank 7 | E38: 0 | M38: 0 | O38: =SUM(G38:N38) -> 0
A39: 8. | B39: Bank 8 | N39: 0 | O39: =SUM(G39:N39) -> 0
E40: =SUM(E32:E37) -> 300 | G40: =SUM(G32:G37) -> 50 | H40: =SUM(H32:H37) -> 200 | I40: =SUM(I32:I37) -> 0 | J40: =SUM(J32:J37) -> 0 | K40: =SUM(K32:K37) -> 0 | L40: =SUM(L32:L37) -> 50 | M40: =SUM(M32:M37) -> 0 | N40: =SUM(N32:N37) -> 0 | O40: =SUM(O32:O37) -> 300
A42: Standort 4
A44: 1. | B44: Bank 1 | E44: 500 | G44: =+E44 -> 500 | O44: =SUM(G44:N44) -> 500
A45: 2. | B45: Bank 2 | H45: =+E45 -> 0 | O45: =SUM(G45:N45) -> 0
A46: 3. | B46: Bank 3 | I46: =+E46 -> 0 | O46: =SUM(G46:N46) -> 0
A47: 4. | B47: Bank 4 | J47: =+E47 -> 0 | O47: =SUM(G47:N47) -> 0
A48: 5. | B48: Bank 5 | K48: =+E48 -> 0 | O48: =SUM(G48:N48) -> 0
A49: 6. | B49: Bank 6 | L49: 0 | O49: =SUM(G49:N49) -> 0
A50: 7. | B50: Bank 7 | M50: 0 | O50: =SUM(G50:N50) -> 0
A51: 8. | B51: Bank 8 | E51: 0 | N51: 0 | O51: =SUM(G51:N51) -> 0
E52: =SUM(E44:E49) -> 500 | G52: =SUM(G44:G49) -> 500 | H52: =SUM(H44:H49) -> 0 | I52: =SUM(I44:I49) -> 0 | J52: =SUM(J44:J49) -> 0 | K52: =SUM(K44:K49) -> 0 | L52: =SUM(L44:L49) -> 0 | M52: =SUM(M44:M49) -> 0 | N52: =SUM(N44:N49) -> 0 | O52: =SUM(O44:O49) -> 500
A54: Holding
A56: 1. | B56: Bank 1 | E56: 150 | G56: =+E56 -> 150 | O56: =SUM(G56:N56) -> 150
A57: 2. | B57: Bank 2 | H57: =+E57 -> 0 | O57: =SUM(G57:N57) -> 0
A58: 3. | B58: Bank 3 | I58: =+E58 -> 0 | O58: =SUM(G58:N58) -> 0
A59: 4. | B59: Bank 4 | E59: 0 | J59: =+E59 -> 0 | O59: =SUM(G59:N59) -> 0
A60: 5. | B60: Bank 5 | K60: =+E60 -> 0 | O60: =SUM(G60:N60) -> 0
A61: 6. | B61: Bank 6 | L61: 0 | O61: =SUM(G61:N61) -> 0
A62: 7. | B62: Bank 7 | M62: 0 | O62: =SUM(G62:N62) -> 0
A63: 8. | B63: Bank 8 | O63: =SUM(G63:N63) -> 0
B64: Bank 9 | E64: 0 | N64: 0 | O64: =SUM(G64:N64) -> 0
E65: =SUM(E56:E61) -> 150 | G65: =SUM(G56:G61) -> 150 | H65: =SUM(H56:H61) -> 0 | I65: =SUM(I56:I61) -> 0 | J65: =SUM(J56:J61) -> 0 | K65: =SUM(K56:K61) -> 0 | L65: =SUM(L56:L61) -> 0 | M65: =SUM(M56:M61) -> 0 | N65: =SUM(N56:N61) -> 0 | O65: =SUM(O56:O61) -> 150
A67: Gesamt-Kreditrahmen
A69: 1. | B69: Bank 1 | E69: =+E8+E20+E32+E44+E56+E64 -> 1250 | G69: =+G8+G20+G32+G44+G56+G64 -> 1250 | H69: =+H8+H20+H32+H44+H56+H64 -> 0 | I69: =+I8+I20+I32+I44+I56+I64 -> 0 | J69: =+J8+J20+J32+J44+J56+J64 -> 0 | K69: =+K8+K20+K32+K44+K56+K64 -> 0 | L69: =+L8+L20+L32+L44+L56+L64 -> 0 | M69: =+M8+M20+M32+M44+M56+M64 -> 0 | N69: =+N8+N20+N32+N44+N56+N64 -> 0 | O69: =SUM(G69:N69) -> 1250
A70: 2. | B70: Bank 2 | E70: =+E9+E21+E33+E45+E57 -> 681.8 | G70: =+G9+G21+G33+G45+G57 -> 0 | H70: =+H9+H21+H33+H45+H57 -> 681.8 | I70: =+I9+I21+I33+I45+I57 -> 0 | J70: =+J9+J21+J33+J45+J57 -> 0 | K70: =+K9+K21+K33+K45+K57 -> 0 | L70: =+L9+L21+L33+L45+L57 -> 0 | M70: =+M9+M21+M33+M45+M57 -> 0 | N70: =+N9+N21+N33+N45+N57 -> 0 | O70: =SUM(G70:N70) -> 681.8
A71: 3. | B71: Bank 3 | E71: =+E10+E22+E34+E46+E58 -> 340.9 | G71: =+G10+G22+G34+G46+G58 -> 0 | H71: =+H10+H22+H34+H46+H58 -> 0 | I71: =+I10+I22+I34+I46+I58 -> 340.9 | J71: =+J10+J22+J34+J46+J58 -> 0 | K71: =+K10+K22+K34+K46+K58 -> 0 | L71: =+L10+L22+L34+L46+L58 -> 0 | M71: =+M10+M22+M34+M46+M58 -> 0 | N71: =+N10+N22+N34+N46+N58 -> 0 | O71: =SUM(G71:N71) -> 340.9
A72: 4. | B72: Bank 4 | E72: =+E11+E23+E35+E47+E59 -> 227.3 | G72: =+G11+G23+G35+G47+G59 -> 0 | H72: =+H11+H23+H35+H47+H59 -> 0 | I72: =+I11+I23+I35+I47+I59 -> 0 | J72: =+J11+J23+J35+J47+J59 -> 227.3 | K72: =+K11+K23+K35+K47+K59 -> 0 | L72: =+L11+L23+L35+L47+L59 -> 0 | M72: =+M11+M23+M35+M47+M59 -> 0 | N72: =+N11+N23+N35+N47+N59 -> 0 | O72: =SUM(G72:N72) -> 227.3
A73: 5. | B73: Bank 5 | E73: =+E12+E24+E36+E48+E60 -> 97.1 | G73: =+G12+G24+G36+G48+G60 -> 0 | H73: =+H12+H24+H36+H48+H60 -> 0 | I73: =+I12+I24+I36+I48+I60 -> 0 | J73: =+J12+J24+J36+J48+J60 -> 0 | K73: =+K12+K24+K36+K48+K60 -> 97.1 | L73: =+L12+L24+L36+L48+L60 -> 0 | M73: =+M12+M24+M36+M48+M60 -> 0 | N73: =+N12+N24+N36+N48+N60 -> 0 | O73: =SUM(G73:N73) -> 97.1
A74: 6. | B74: Bank 6 | E74: =+E13+E25+E37+E49+E61 -> 50 | G74: =+G13+G25+G37+G49+G61 -> 0 | H74: =+H13+H25+H37+H49+H61 -> 0 | I74: =+I13+I25+I37+I49+I61 -> 0 | J74: =+J13+J25+J37+J49+J61 -> 0 | K74: =+K13+K25+K37+K49+K61 -> 0 | L74: =+L13+L25+L37+L49+L61 -> 50 | M74: =+M13+M25+M37+M49+M61 -> 0 | N74: =+N13+N25+N37+N49+N61 -> 0 | O74: =SUM(G74:N74) -> 50
A75: 7. | B75: Bank 7 | E75: =+E14+E26+E38+E50+E62 -> 25.6 | G75: =+G14+G26+G38+G50+G62 -> 0 | H75: =+H14+H26+H38+H50+H62 -> 0 | I75: =+I14+I26+I38+I50+I62 -> 0 | J75: =+J14+J26+J38+J50+J62 -> 0 | K75: =+K14+K26+K38+K50+K62 -> 0 | L75: =+L14+L26+L38+L50+L62 -> 0 | M75: =+M14+M26+M38+M50+M62 -> 25.6 | N75: =+N14+N26+N38+N50+N62 -> 0 | O75: =SUM(G75:N75) -> 25.6
A76: 8. | B76: Bank 8 | E76: =+E15+E27+E39+E51+E63 -> 0 | G76: =+G15+G27+G39+G51+G63 -> 0 | H76: =+H15+H27+H39+H51+H63 -> 0 | I76: =+I15+I27+I39+I51+I63 -> 0 | J76: =+J15+J27+J39+J51+J63 -> 0 | K76: =+K15+K27+K39+K51+K63 -> 0 | L76: =+L15+L27+L39+L51+L63 -> 0 | M76: =+M15+M27+M39+M51+M63 -> 0 | N76: =+N15+N27+N39+N51+N63 -> 0 | O76: =SUM(G76:N76) -> 0
E77: =SUM(E69:E76) -> 2672.7 | G77: =SUM(G69:G76) -> 1250 | H77: =SUM(H69:H76) -> 681.8 | I77: =SUM(I69:I76) -> 340.9 | J77: =SUM(J69:J76) -> 227.3 | K77: =SUM(K69:K76) -> 97.1 | L77: =SUM(L69:L76) -> 50 | M77: =SUM(M69:M76) -> 25.6 | N77: =SUM(N69:N76) -> 0 | O77: =SUM(O69:O76) -> 2672.7

Sheet Standort 1
A1: Standort 1 | I1: geplant
J2: Name | K2: Datum
A3: Liquiditätsplanung aufgrund der Einzelkonten
A4: Planung in T€
E5: =+Holding!E5 -> Montag | F5: =+Holding!F5 -> Dienstag | G5: =+Holding!G5 -> Mittwoch | H5: =+Holding!H5 -> Donnerstag | I5: =+Holding!I5 -> Freitag | J5: =+Holding!J5 -> Samstag | K5: =+Holding!K5 -> Sonntag | L5: =+Holding!L5 -> Montag
E6: 45870 | F6: =+E6+1 -> 45871 | G6: =+F6+1 -> 45872 | H6: =+G6+1 -> 45873 | I6: =+H6+1 -> 45874 | J6: =+I6+1 -> 45875 | K6: =+J6+1 -> 45876 | L6: =+K6+1 -> 45877
D7: Text | E7: T€ | F7: T€ | G7: T€ | H7: T€ | I7: T€ | J7: T€ | K7: T€ | L7: T€
A8: Bank 1 | E8: Konto-Nr.
D10: Saldo zum Tagesbeginn | E10: -649.5 | F10: =+E41 -> -708.93 | G10: =+F41 -> -652.6 | H10: =+G41 -> -592.6 | I10: =+H41 -> -570.793 | J10: =+I41 -> -565.977 | K10: =+J41 -> -565.977 | L10: =+K41 -> -565.977
A11: Einnahmen
B12: Debitoren | E12: =50+6.5+26+12.089 -> 94.589 | F12: =30+15.2+17.13 -> 62.33 | G12: =15+15 -> 30 | H12: =20+1.349+0.458 -> 21.807 | I12: =20+17.9 -> 37.9 | L12: 20
B13: Verbund
B14: Hersteller Bank 1
B15: Schecks
B16: Hersteller Bank 2
B21: Geldverkehr | G21: 80
D22: Summe Einnahmen | E22: =SUM(E11:E21) -> 94.589 | F22: =SUM(F11:F21) -> 62.33 | G22: =SUM(G11:G21) -> 110 | H22: =SUM(H11:H21) -> 21.807 | I22: =SUM(I11:I21) -> 37.9 | J22: =SUM(J11:J21) -> 0 | K22: =SUM(K11:K21) -> 0 | L22: =SUM(L11:L21) -> 20
A23: Ausgaben
B24: Lohn/Gehalt
B25: Lohnsteuer | E25: =37.619-3.6 -> 34.019
B26: Sozialversicherung | I26: 13.084
B27: Mieten
B28: Ablösung Fzge
B29: Hersteller Bank 1
B30: Kreditoren
B31: Zinsen
B32: Schecks
B36: Geldtransit | E36: 120 | F36: 6 | G36: 50 | I36: 20 | L36: 40
B37: Umsatzsteuer
B38: Geldverkehr
D39: Summe Ausgaben | E39: =SUM(E24:E38) -> 154.019 | F39: =SUM(F24:F38) -> 6 | G39: =SUM(G24:G38) -> 50 | H39: =SUM(H24:H38) -> 0 | I39: =SUM(I24:I38) -> 33.084 | J39: =SUM(J24:J38) -> 0 | K39: =SUM(K24:K38) -> 0 | L39: =SUM(L24:L38) -> 40
D40: Saldo Einnahmen ./. Ausgaben | E40: =+E22-E39 -> -59.43 | F40: =+F22-F39 -> 56.33 | G40: =+G22-G39 -> 60 | H40: =+H22-H39 -> 21.807 | I40: =+I22-I39 -> 4.816 | J40: =+J22-J39 -> 0 | K40: =+K22-K39 -> 0 | L40: =+L22-L39 -> -20
D41: Tagesendsaldo | E41: =+E10+E40 -> -708.93 | F41: =+F10+F40 -> -652.6 | G41: =+G10+G40 -> -592.6 | H41: =+H10+H40 -> -570.793 | I41: =+I10+I40 -> -565.977 | J41: =+J10+J40 -> -565.977 | K41: =+K10+K40 -> -565.977 | L41: =+L10+L40 -> -585.977
A43: Bank 2 | E43: Konto-Nr. | F43: 0
D45: Saldo zum Tagesbeginn | F45: =E75 -> 0 | G45: =F75 -> 0 | H45: =G75 -> 0 | I45: =H75 -> 0 | J45: =I75 -> 0 | K45: =J75 -> 0 | L45: =K75 -> 0
A46: Einnahmen
B55: Geldverkehr
D56: Summe Einnahmen | E56: =SUM(E46:E55) -> 0 | F56: =SUM(F46:F55) -> 0 | G56: =SUM(G46:G55) -> 0 | H56: =SUM(H46:H55) -> 0 | I56: =SUM(I46:I55) -> 0 | J56: =SUM(J46:J55) -> 0 | K56: =SUM(K46:K55) -> 0 | L56: =SUM(L46:L55) -> 0
A57: Ausgaben
B72: Geldverkehr
D73: Summe Ausgaben | E73: =SUM(E58:E72) -> 0 | F73: =SUM(F58:F72) -> 0 | G73: =SUM(G58:G72) -> 0 | H73: =SUM(H58:H72) -> 0 | I73: =SUM(I58:I72) -> 0 | J73: =SUM(J58:J72) -> 0 | K73: =SUM(K58:K72) -> 0 | L73: =SUM(L58:L72) -> 0
D74: Saldo Einnahmen ./. Ausgaben | E74: =+E56-E73 -> 0 | F74: =+F56-F73 -> 0 | G74: =+G56-G73 -> 0 | H74: =+H56-H73 -> 0 | I74: =+I56-I73 -> 0 | J74: =+J56-J73 -> 0 | K74: =+K56-K73 -> 0 | L74: =+L56-L73 -> 0
D75: Tagesendsaldo | E75: =+E45+E74 -> 0 | F75: =+F45+F74 -> 0 | G75: =+G45+G74 -> 0 | H75: =+H45+H74 -> 0 | I75: =+I45+I74 -> 0 | J75: =+J45+J74 -> 0 | K75: =+K45+K74 -> 0 | L75: =+L45+L74 -> 0
A77: Bank 2 | E77: Konto-Nr.
D79: Saldo zum Tagesbeginn | E79: -284.1 | F79: =+E109 -> -239.29 | G79: =+F109 -> -224.0498 | H79: =+G109 -> -287.0788 | I79: =+H109 -> -242.0788 | J79: =+I109 -> -231.3278 | K79: =+J109 -> -231.3278 | L79: =+K109 -> -231.3278
A80: Einnahmen
B81: Debitoren | E81: 5 | F81: 5 | G81: 5 | H81: 5 | I81: 5 | L81: 5
B82: Kasse | E82: 80 | F82: 50 | G82: 10 | H82: 40 | I82: 10 | L82: 10
B83: Schecks | G83: 45
B90: Geldverkehr
D91: Summe Einnahmen | E91: =SUM(E80:E90) -> 85 | F91: =SUM(F80:F90) -> 55 | G91: =SUM(G80:G90) -> 60 | H91: =SUM(H80:H90) -> 45 | I91: =SUM(I80:I90) -> 15 | J91: =SUM(J80:J90) -> 0 | K91: =SUM(K80:K90) -> 0 | L91: =SUM(L80:L90) -> 15
A92: Ausgaben
B93: Ablösung Fzge. | E93: =23.19+17 -> 40.19 | F93: =20.4378+19.322 -> 39.7598
B94: Kreditoren | G94: 20
B95: Schecks
B96: Zinsen
B97: Verbund | G97: 20
G99: 3.029 | I99: =1.925+2.324 -> 4.249
B105: Umsatzsteuer
B106: Geldverkehr | G106: 80
D107: Summe Ausgaben | E107: =SUM(E93:E106) -> 40.19 | F107: =SUM(F93:F106) -> 39.7598 | G107: =SUM(G93:G106) -> 123.029 | H107: =SUM(H93:H106) -> 0 | I107: =SUM(I93:I106) -> 4.249 | J107: =SUM(J93:J106) -> 0 | K107: =SUM(K93:K106) -> 0 | L107: =SUM(L93:L106) -> 0
D108: Saldo Einnahmen ./. Ausgaben | E108: =+E91-E107 -> 44.81 | F108: =+F91-F107 -> 15.2402 | G108: =+G91-G107 -> -63.029 | H108: =+H91-H107 -> 45 | I108: =+I91-I107 -> 10.751 | J108: =+J91-J107 -> 0 | K108: =+K91-K107 -> 0 | L108: =+L91-L107 -> 15
D109: Tagesendsaldo | E109: =+E79+E108 -> -239.29 | F109: =+F79+F108 -> -224.0498 | G109: =+G79+G108 -> -287.0788 | H109: =+H79+H108 -> -242.0788 | I109: =+I79+I108 -> -231.3278 | J109: =+J79+J108 -> -231.3278 | K109: =+K79+K108 -> -231.3278 | L109: =+L79+L108 -> -216.3278
A111: Bank 3 | E111: Konto-Nr.
D113: Saldo zum Tagesbeginn | E113: -205 | F113: =+E143 -> -205 | G113: =+F143 -> -197.51 | H113: =+G143 -> -196.691 | I113: =+H143 -> -194.869 | J113: =+I143 -> -193.869 | K113: =+J143 -> -193.869 | L113: =+K143 -> -193.869
A114: Einnahmen
B115: Kreditkarten | F115: =4.1+1.8 -> 5.9
B116: TeleCash | F116: 1.59 | G116: 0.819 | H116: 1.822 | I116: 1 | L116: 1
B123: Geldtransit
B124: Geldverkehr
D125: Summe Einnahmen | E125: =SUM(E114:E124) -> 0 | F125: =SUM(F114:F124) -> 7.49 | G125: =SUM(G114:G124) -> 0.819 | H125: =SUM(H114:H124) -> 1.822 | I125: =SUM(I114:I124) -> 1 | J125: =SUM(J114:J124) -> 0 | K125: =SUM(K114:K124) -> 0 | L125: =SUM(L114:L124) -> 1
A126: Ausgaben
B127: Zinsen
B139: Geldtransit
B140: Geldverkehr
D141: Summe Ausgaben | E141: =SUM(E127:E140) -> 0 | F141: =SUM(F127:F140) -> 0 | G141: =SUM(G127:G140) -> 0 | H141: =SUM(H127:H140) -> 0 | I141: =SUM(I127:I140) -> 0 | J141: =SUM(J127:J140) -> 0 | K141: =SUM(K127:K140) -> 0 | L141: =SUM(L127:L140) -> 0
D142: Saldo Einnahmen ./. Ausgaben | E142: =+E125-E141 -> 0 | F142: =+F125-F141 -> 7.49 | G142: =+G125-G141 -> 0.819 | H142: =+H125-H141 -> 1.822 | I142: =+I125-I141 -> 1 | J142: =+J125-J141 -> 0 | K142: =+K125-K141 -> 0 | L142: =+L125-L141 -> 1
D143: Tagesendsaldo | E143: =+E113+E142 -> -205 | F143: =+F113+F142 -> -197.51 | G143: =+G113+G142 -> -196.691 | H143: =+H113+H142 -> -194.869 | I143: =+I113+I142 -> -193.869 | J143: =+J113+J142 -> -193.869 | K143: =+K113+K142 -> -193.869 | L143: =+L113+L142 -> -192.869
A145: Hersteller Bank 1 | E145: Konto-Nr.
D147: Saldo zum Tagesbeginn | E147: -4.2 | F147: =+E177 -> -65.346 | G147: =+F177 -> -67.742 | H147: =+G177 -> -63.7277 | I147: =+H177 -> -92.0567 | J147: =+I177 -> -97.0697 | K147: =+J177 -> -97.0697 | L147: =+K177 -> -97.0697
A148: Einnahmen
B149: KF / KL | E149: =22.053+3.4+12 -> 37.453 | F149: =12.191 -> 12.191 | G149: =6.3+10.45+19.6723 -> 36.4223
B150: GW Einfinanzierung | E150: =4.277 -> 4.277 | F150: 7.924 | H150: 10
B151: TeleCash | E151: 1.5 | F151: 1.5 | G151: 1.5 | H151: 1.5 | I151: 1.5 | L151: 1.5
B152: Debitoren
B157: Geldtransit | E157: 6 | F157: 50 | H157: 20 | I157: 40
B158: Geldverkehr
D159: Summe Einnahmen | E159: =SUM(E148:E158) -> 49.23 | F159: =SUM(F148:F158) -> 71.615 | G159: =SUM(G148:G158) -> 37.9223 | H159: =SUM(H148:H158) -> 31.5 | I159: =SUM(I148:I158) -> 41.5 | J159: =SUM(J148:J158) -> 0 | K159: =SUM(K148:K158) -> 0 | L159: =SUM(L148:L158) -> 1.5
A160: Ausgaben
B161: GW Ablösung | E161: 12
B162: NW Ablösung | E162: 98.376 | F162: =16.42+8+3+5.753+20.419+20.419 -> 74.011 | G162: =19.294+14.614 -> 33.908 | H162: =6.2+19.688+7.389+4.2+10.2+12.152 -> 59.829 | I162: =15.158+19.07+12.285 -> 46.513 | L162: 20
B163: Teilefinanzierung
B164: Tilgungen / Zinsen
B165: NW Temporär
B166: Kreditoren
B167: Mietwagenprämie
B173: Geldtransit
B174: Geldverkehr
D175: Summe Ausgaben | E175: =SUM(E161:E174) -> 110.376 | F175: =SUM(F161:F174) -> 74.011 | G175: =SUM(G161:G174) -> 33.908 | H175: =SUM(H161:H174) -> 59.829 | I175: =SUM(I161:I174) -> 46.513 | J175: =SUM(J161:J174) -> 0 | K175: =SUM(K161:K174) -> 0 | L175: =SUM(L161:L174) -> 20
D176: Saldo Einnahmen ./. Ausgaben | E176: =+E159-E175 -> -61.146 | F176: =+F159-F175 -> -2.396 | G176: =+G159-G175 -> 4.0143 | H176: =+H159-H175 -> -28.329 | I176: =+I159-I175 -> -5.013 | J176: =+J159-J175 -> 0 | K176: =+K159-K175 -> 0 | L176: =+L159-L175 -> -18.5
...

Sheet Standort 2
A1: Standort 2 | I1: geplant | K1: 38971
J2: Name
A3: Liquiditätsplanung aufgrund der Einzelkonten
A4: Planung in T€
E5: =+Holding!E5 -> Montag | F5: =+Holding!F5 -> Dienstag | G5: =+Holding!G5 -> Mittwoch | H5: =+Holding!H5 -> Donnerstag | I5: =+Holding!I5 -> Freitag | J5: =+Holding!J5 -> Samstag | K5: =+Holding!K5 -> Sonntag | L5: =+Holding!L5 -> Montag
E6: 45870 | F6: =+E6+1 -> 45871 | G6: =+F6+1 -> 45872 | H6: =+G6+1 -> 45873 | I6: =+H6+1 -> 45874 | J6: =+I6+1 -> 45875 | K6: =+J6+1 -> 45876 | L6: =+K6+1 -> 45877
D7: Text | E7: T€ | F7: T€ | G7: T€ | H7: T€ | I7: T€ | J7: T€ | K7: T€ | L7: T€
A8: =+Grunddaten!B20 -> Bank 1 | E8: Konto-Nr. | F8: =+Grunddaten!D20 -> 0
D10: Saldo zum Tagesbeginn | E10: 140 | F10: =+E41 -> 108.6 | G10: =+F41 -> 53.3 | H10: =+G41 -> 53.3 | I10: =+H41 -> 53.3 | J10: =+I41 -> 25.3 | K10: =+J41 -> 25.3 | L10: =+K41 -> 25.3
A11: Einnahmen
D12: Debitoren
D14: Scheck retuer
B20: Geldverkehr
D21: Summe Einnahmen | E21: =SUM(E11:E20) -> 0 | F21: =SUM(F11:F20) -> 0 | G21: =SUM(G11:G20) -> 0 | H21: =SUM(H11:H20) -> 0 | I21: =SUM(I11:I20) -> 0 | J21: =SUM(J11:J20) -> 0 | K21: =SUM(K11:K20) -> 0 | L21: =SUM(L11:L20) -> 0
A22: Ausgaben
D23: Leasingauslauf | E23: 1.5
D24: GW-Ankauf
D25: Diverse
D26: Stundung
D27: Verbundene
D28: kreditoren | I28: 28
D29: Ablöse FB
D30: Ablöse FB EF temp. | E30: 29.9 | F30: =18.8+8.6+27.9 -> 55.3
B38: Geldverkehr
D39: Summe Ausgaben | E39: =SUM(E23:E38) -> 31.4 | F39: =SUM(F23:F38) -> 55.3 | G39: =SUM(G23:G38) -> 0 | H39: =SUM(H23:H38) -> 0 | I39: =SUM(I23:I38) -> 28 | J39: =SUM(J23:J38) -> 0 | K39: =SUM(K23:K38) -> 0 | L39: =SUM(L23:L38) -> 0
D40: Saldo Einnahmen ./. Ausgaben | E40: =+E21-E39 -> -31.4 | F40: =+F21-F39 -> -55.3 | G40: =+G21-G39 -> 0 | H40: =+H21-H39 -> 0 | I40: =+I21-I39 -> -28 | J40: =+J21-J39 -> 0 | K40: =+K21-K39 -> 0 | L40: =+L21-L39 -> 0
D41: Tagesendsaldo | E41: =+E10+E40 -> 108.6 | F41: =+F10+F40 -> 53.3 | G41: =+G10+G40 -> 53.3 | H41: =+H10+H40 -> 53.3 | I41: =+I10+I40 -> 25.3 | J41: =+J10+J40 -> 25.3 | K41: =+K10+K40 -> 25.3 | L41: =+L10+L40 -> 25.3
A43: =+Grunddaten!B21 -> Bank 2 | E43: Konto-Nr. | F43: =+Grunddaten!D21 -> 0
D45: Saldo zum Tagesbeginn | E45: -205.8 | F45: =E75 -> -302.5 | G45: =F75 -> -346 | H45: =G75 -> -419.1 | I45: =H75 -> -430.7 | J45: =I75 -> -431.6 | K45: =J75 -> -431.6 | L45: =K75 -> -431.6
A46: Einnahmen
D47: Debitoren | E47: 10 | F47: 10 | G47: 10 | H47: 10 | I47: 10
D48: Kasse | E48: 20.6
D49: geplante AL Kasse | F49: 8 | G49: 16.7
D50: Debitoren Verbund
D52: Auslieferung Überw.
B55: Geldverkehr
D56: Summe Einnahmen | E56: =SUM(E46:E55) -> 30.6 | F56: =SUM(F46:F55) -> 18 | G56: =SUM(G46:G55) -> 26.7 | H56: =SUM(H46:H55) -> 10 | I56: =SUM(I46:I55) -> 10 | J56: =SUM(J46:J55) -> 0 | K56: =SUM(K46:K55) -> 0 | L56: =SUM(L46:L55) -> 0
A57: Ausgaben
D58: GW-Ankauf | E58: 11.2
D59: Diverse | I59: 10.9
D60: Umsatzsteuer | E60: 80.7
D61: Lohnsteuer | E61: 25
D62: Zahlung Kreditoren
D63: Leasingauslauf
D64: Ablöse EF Temp. | E64: 10.4 | F64: =18.8+11.7 -> 30.5 | G64: 40.5 | H64: 21.6
D65: Lohn
D66: Sozialversicherungen
D67: Miete
D68: Darlehen + Zinsen
D69: Stundung
D70: Lohn/Gehalt
B72: Geldverkehr | F72: 31 | G72: 59.3
D73: Summe Ausgaben | E73: =SUM(E58:E72) -> 127.3 | F73: =SUM(F58:F72) -> 61.5 | G73: =SUM(G58:G72) -> 99.8 | H73: =SUM(H58:H72) -> 21.6 | I73: =SUM(I58:I72) -> 10.9 | J73: =SUM(J58:J72) -> 0 | K73: =SUM(K58:K72) -> 0 | L73: =SUM(L58:L72) -> 0
D74: Saldo Einnahmen ./. Ausgaben | E74: =+E56-E73 -> -96.7 | F74: =+F56-F73 -> -43.5 | G74: =+G56-G73 -> -73.1 | H74: =+H56-H73 -> -11.6 | I74: =+I56-I73 -> -0.9 | J74: =+J56-J73 -> 0 | K74: =+K56-K73 -> 0 | L74: =+L56-L73 -> 0
D75: Tagesendsaldo | E75: =+E45+E74 -> -302.5 | F75: =+F45+F74 -> -346 | G75: =+G45+G74 -> -419.1 | H75: =+H45+H74 -> -430.7 | I75: =+I45+I74 -> -431.6 | J75: =+J45+J74 -> -431.6 | K75: =+K45+K74 -> -431.6 | L75: =+L45+L74 -> -431.6
A77: =+Grunddaten!B22 -> Bank 3 | E77: Konto-Nr. | F77: =+Grunddaten!D22 -> 0
D79: Saldo zum Tagesbeginn | E79: 0 | F79: =+E109 -> 0 | G79: =+F109 -> 0 | H79: =+G109 -> 0 | I79: =+H109 -> 0 | J79: =+I109 -> 0 | K79: =+J109 -> 0 | L79: =+K109 -> 0
A80: Einnahmen
B90: Geldverkehr
D91: Summe Einnahmen | E91: =SUM(E80:E90) -> 0 | F91: =SUM(F80:F90) -> 0 | G91: =SUM(G80:G90) -> 0 | H91: =SUM(H80:H90) -> 0 | I91: =SUM(I80:I90) -> 0 | J91: =SUM(J80:J90) -> 0 | K91: =SUM(K80:K90) -> 0 | L91: =SUM(L80:L90) -> 0
A92: Ausgaben
B106: Geldverkehr
D107: Summe Ausgaben | E107: =SUM(E93:E106) -> 0 | F107: =SUM(F93:F106) -> 0 | G107: =SUM(G93:G106) -> 0 | H107: =SUM(H93:H106) -> 0 | I107: =SUM(I93:I106) -> 0 | J107: =SUM(J93:J106) -> 0 | K107: =SUM(K93:K106) -> 0 | L107: =SUM(L93:L106) -> 0
D108: Saldo Einnahmen ./. Ausgaben | E108: =+E91-E107 -> 0 | F108: =+F91-F107 -> 0 | G108: =+G91-G107 -> 0 | H108: =+H91-H107 -> 0 | I108: =+I91-I107 -> 0 | J108: =+J91-J107 -> 0 | K108: =+K91-K107 -> 0 | L108: =+L91-L107 -> 0
D109: Tagesendsaldo | E109: =+E79+E108 -> 0 | F109: =+F79+F108 -> 0 | G109: =+G79+G108 -> 0 | H109: =+H79+H108 -> 0 | I109: =+I79+I108 -> 0 | J109: =+J79+J108 -> 0 | K109: =+K79+K108 -> 0 | L109: =+L79+L108 -> 0
A111: =+Grunddaten!B23 -> Bank 4 | E111: Konto-Nr. | F111: =+Grunddaten!D23 -> 0
D113: Saldo zum Tagesbeginn | E113: 0 | F113: =+E143 -> 0 | G113: =+F143 -> 0 | H113: =+G143 -> 0 | I113: =+H143 -> 0 | J113: =+I143 -> 0 | K113: =+J143 -> 0 | L113: =+K143 -> 0
A114: Einnahmen
B124: Geldverkehr
D125: Summe Einnahmen | E125: =SUM(E114:E124) -> 0 | F125: =SUM(F114:F124) -> 0 | G125: =SUM(G114:G124) -> 0 | H125: =SUM(H114:H124) -> 0 | I125: =SUM(I114:I124) -> 0 | J125: =SUM(J114:J124) -> 0 | K125: =SUM(K114:K124) -> 0 | L125: =SUM(L114:L124) -> 0
A126: Ausgaben
B140: Geldverkehr
D141: Summe Ausgaben | E141: =SUM(E127:E140) -> 0 | F141: =SUM(F127:F140) -> 0 | G141: =SUM(G127:G140) -> 0 | H141: =SUM(H127:H140) -> 0 | I141: =SUM(I127:I140) -> 0 | J141: =SUM(J127:J140) -> 0 | K141: =SUM(K127:K140) -> 0 | L141: =SUM(L127:L140) -> 0
D142: Saldo Einnahmen ./. Ausgaben | E142: =+E125-E141 -> 0 | F142: =+F125-F141 -> 0 | G142: =+G125-G141 -> 0 | H142: =+H125-H141 -> 0 | I142: =+I125-I141 -> 0 | J142: =+J125-J141 -> 0 | K142: =+K125-K141 -> 0 | L142: =+L125-L141 -> 0
D143: Tagesendsaldo | E143: =+E113+E142 -> 0 | F143: =+F113+F142 -> 0 | G143: =+G113+G142 -> 0 | H143: =+H113+H142 -> 0 | I143: =+I113+I142 -> 0 | J143: =+J113+J142 -> 0 | K143: =+K113+K142 -> 0 | L143: =+L113+L142 -> 0
A145: =+Grunddaten!B24 -> Bank 5 | E145: Konto-Nr. | F145: =+Grunddaten!D24 -> 0
D147: Saldo zum Tagesbeginn | E147: 2.1 | F147: =+E177 -> 0 | G147: =+F177 -> 0 | H147: =+G177 -> 0 | I147: =+H177 -> 0 | J147: =+I177 -> 0 | K147: =+J177 -> 0 | L147: =+K177 -> 0
A148: Einnahmen
D149: KF/KL | F149: 44.2 | G149: 24.9 | I149: 28.6
D150: Ford Werke
D151: Debitoren | G151: 5
D152: GW Finanz.
D153: Prämien
B158: Geldverkehr | E158: 31 | F158: 59.3
D159: Summe Einnahmen | E159: =SUM(E148:E158) -> 31 | F159: =SUM(F148:F158) -> 103.5 | G159: =SUM(G148:G158) -> 29.9 | H159: =SUM(H148:H158) -> 0 | I159: =SUM(I148:I158) -> 28.6 | J159: =SUM(J148:J158) -> 0 | K159: =SUM(K148:K158) -> 0 | L159: =SUM(L148:L158) -> 0
A160: Ausgaben
D161: Restzahliung Lohn | E161: 9.9
D162: GW Ankauf
D163: Leasingauslauf
D164: Zahlung Verbundene
D165: Ablöse EF FB | F165: 93.7 | G165: 6.6
E166: =4.6+3.1 -> 7.7 | F166: 9.8
D167: Kreditoren | E167: 15.5 | I167: 28.6
D168: Stundung
D169: Zinsen
D170: Tilgung
G171: 23.3
B174: Geldverkehr
D175: Summe Ausgaben | E175: =SUM(E161:E174) -> 33.1 | F175: =SUM(F161:F174) -> 103.5 | G175: =SUM(G161:G174) -> 29.9 | H175: =SUM(H161:H174) -> 0 | I175: =SUM(I161:I174) -> 28.6 | J175: =SUM(J161:J174) -> 0 | K175: =SUM(K161:K174) -> 0 | L175: =SUM(L161:L174) -> 0
D176: Saldo Einnahmen ./. Ausgaben | E176: =+E159-E175 -> -2.1 | F176: =+F159-F175 -> 0 | G176: =+G159-G175 -> 0 | H176: =+H159-H175 -> 0 | I176: =+I159-I175 -> 0 | J176: =+J159-J175 -> 0 | K176: =+K159-K175 -> 0 | L176: =+L159-L175 -> 0
...

Sheet Standort 3
A1: Standort 3 | I1: geplant
J2: Name | K2: Datum
A3: Liquiditätsplanung aufgrund der Einzelkonten
A4: Planung in T€
E5: =+Holding!E5 -> Montag | F5: =+Holding!F5 -> Dienstag | G5: =+Holding!G5 -> Mittwoch | H5: =+Holding!H5 -> Donnerstag | I5: =+Holding!I5 -> Freitag | J5: =+Holding!J5 -> Samstag | K5: =+Holding!K5 -> Sonntag | L5: =+Holding!L5 -> Montag
E6: 45870 | F6: =+E6+1 -> 45871 | G6: =+F6+1 -> 45872 | H6: =+G6+1 -> 45873 | I6: =+H6+1 -> 45874 | J6: =+I6+1 -> 45875 | K6: =+J6+1 -> 45876 | L6: =+K6+1 -> 45877
D7: Text | E7: T€ | F7: T€ | G7: T€ | H7: T€ | I7: T€ | J7: T€ | K7: T€ | L7: T€
A8: =+Grunddaten!B32 -> Bank 1 | E8: Konto-Nr. | F8: =+Grunddaten!D32 -> 0
D10: Saldo zum Tagesbeginn | E10: 72.9 | F10: =+E41 -> 72.9 | G10: =+F41 -> 75.9 | H10: =+G41 -> 78.9 | I10: =+H41 -> 81.9 | J10: =+I41 -> 84.9 | K10: =+J41 -> 84.9 | L10: =+K41 -> 84.9
A11: Einnahmen
B12: Debitoren | F12: 3 | G12: 3 | H12: 3 | I12: 3 | L12: 3
B13: Kasse
B21: Geldverkehr
D22: Summe Einnahmen | E22: =SUM(E11:E21) -> 0 | F22: =SUM(F11:F21) -> 3 | G22: =SUM(G11:G21) -> 3 | H22: =SUM(H11:H21) -> 3 | I22: =SUM(I11:I21) -> 3 | J22: =SUM(J11:J21) -> 0 | K22: =SUM(K11:K21) -> 0 | L22: =SUM(L11:L21) -> 3
A23: Ausgaben
B24: Lohn/Gehalt
B25: Lohnsteuer
B26: Sozialversicherung
B27: Mieten
B28: Ablösung Fahrzeuge
B29: Zahlung Kreditoren Verb.
B30: Zahlung Leasingablös.
B31: Zahlung Vergleich
B32: Umbuchung
B33: Zinsen
B38: Geldverkehr
D39: Summe Ausgaben | E39: =SUM(E24:E38) -> 0 | F39: =SUM(F24:F38) -> 0 | G39: =SUM(G24:G38) -> 0 | H39: =SUM(H24:H38) -> 0 | I39: =SUM(I24:I38) -> 0 | J39: =SUM(J24:J38) -> 0 | K39: =SUM(K24:K38) -> 0 | L39: =SUM(L24:L38) -> 0
D40: Saldo Einnahmen ./. Ausgaben | E40: =+E22-E39 -> 0 | F40: =+F22-F39 -> 3 | G40: =+G22-G39 -> 3 | H40: =+H22-H39 -> 3 | I40: =+I22-I39 -> 3 | J40: =+J22-J39 -> 0 | K40: =+K22-K39 -> 0 | L40: =+L22-L39 -> 3
D41: Tagesendsaldo | E41: =+E10+E40 -> 72.9 | F41: =+F10+F40 -> 75.9 | G41: =+G10+G40 -> 78.9 | H41: =+H10+H40 -> 81.9 | I41: =+I10+I40 -> 84.9 | J41: =+J10+J40 -> 84.9 | K41: =+K10+K40 -> 84.9 | L41: =+L10+L40 -> 87.9
A43: =+Grunddaten!B33 -> Bank 2 | E43: Konto-Nr. | F43: =+Grunddaten!D33 -> 0
D45: Saldo zum Tagesbeginn | E45: -104.1 | F45: =E75 -> -183.1 | G45: =F75 -> -193.1 | H45: =G75 -> -198.1 | I45: =H75 -> -192.8 | J45: =I75 -> -202.8 | K45: =J75 -> -202.8 | L45: =K75 -> -202.8
A46: Einnahmen
B47: Debitoren | F47: 20 | G47: 15 | H47: 20 | I47: 20 | L47: 20
B48: Kasse | E48: 9.4
B50: Umsatzsteuer
B55: Geldverkehr
D56: Summe Einnahmen | E56: =SUM(E46:E55) -> 9.4 | F56: =SUM(F46:F55) -> 20 | G56: =SUM(G46:G55) -> 15 | H56: =SUM(H46:H55) -> 20 | I56: =SUM(I46:I55) -> 20 | J56: =SUM(J46:J55) -> 0 | K56: =SUM(K46:K55) -> 0 | L56: =SUM(L46:L55) -> 20
A57: Ausgaben
B58: Loh/Gehalt
B59: Lohnsteuer | E59: 21.8
B60: Sozialversicherung
B61: Mieten
B62: Ablös. Fahrzeuge | E62: 28.7 | G62: 20 | I62: 10
B63: Zahlung Kred. | E63: 5 | H63: 8 | I63: 20
B64: Zinsen/Tilgung
B65: Umsatzsteuer | E65: 12.3
B66: Gew. Steuer
B67: Beitrag Maschinenb. | H67: 6.7
B68: Grundsteuer
B70: Zlg. An AGG | C70: Verb.U. | F70: 30 | L70: 15
B72: Geldverkehr/Kontoauff. | E72: 20.6
D73: Summe Ausgaben | E73: =SUM(E58:E72) -> 88.4 | F73: =SUM(F58:F72) -> 30 | G73: =SUM(G58:G72) -> 20 | H73: =SUM(H58:H72) -> 14.7 | I73: =SUM(I58:I72) -> 30 | J73: =SUM(J58:J72) -> 0 | K73: =SUM(K58:K72) -> 0 | L73: =SUM(L58:L72) -> 15
D74: Saldo Einnahmen ./. Ausgaben | E74: =+E56-E73 -> -79 | F74: =+F56-F73 -> -10 | G74: =+G56-G73 -> -5 | H74: =+H56-H73 -> 5.3 | I74: =+I56-I73 -> -10 | J74: =+J56-J73 -> 0 | K74: =+K56-K73 -> 0 | L74: =+L56-L73 -> 5
D75: Tagesendsaldo | E75: =+E45+E74 -> -183.1 | F75: =+F45+F74 -> -193.1 | G75: =+G45+G74 -> -198.1 | H75: =+H45+H74 -> -192.8 | I75: =+I45+I74 -> -202.8 | J75: =+J45+J74 -> -202.8 | K75: =+K45+K74 -> -202.8 | L75: =+L45+L74 -> -197.8
A77: =+Grunddaten!B34 -> Bank 3 | E77: Konto-Nr.
D79: Saldo zum Tagesbeginn | E79: 0 | F79: =+E109 -> 0 | G79: =+F109 -> 0 | H79: =+G109 -> 0 | I79: =+H109 -> 0 | J79: =+I109 -> 0 | K79: =+J109 -> 0 | L79: =+K109 -> 0
A80: Einnahmen
B90: Geldverkehr
D91: Summe Einnahmen | E91: =SUM(E80:E90) -> 0 | F91: =SUM(F80:F90) -> 0 | G91: =SUM(G80:G90) -> 0 | H91: =SUM(H80:H90) -> 0 | I91: =SUM(I80:I90) -> 0 | J91: =SUM(J80:J90) -> 0 | K91: =SUM(K80:K90) -> 0 | L91: =SUM(L80:L90) -> 0
A92: Ausgaben
B106: Geldverkehr
D107: Summe Ausgaben | E107: =SUM(E93:E106) -> 0 | F107: =SUM(F93:F106) -> 0 | G107: =SUM(G93:G106) -> 0 | H107: =SUM(H93:H106) -> 0 | I107: =SUM(I93:I106) -> 0 | J107: =SUM(J93:J106) -> 0 | K107: =SUM(K93:K106) -> 0 | L107: =SUM(L93:L106) -> 0
D108: Saldo Einnahmen ./. Ausgaben | E108: =+E91-E107 -> 0 | F108: =+F91-F107 -> 0 | G108: =+G91-G107 -> 0 | H108: =+H91-H107 -> 0 | I108: =+I91-I107 -> 0 | J108: =+J91-J107 -> 0 | K108: =+K91-K107 -> 0 | L108: =+L91-L107 -> 0
D109: Tagesendsaldo | E109: =+E79+E108 -> 0 | F109: =+F79+F108 -> 0 | G109: =+G79+G108 -> 0 | H109: =+H79+H108 -> 0 | I109: =+I79+I108 -> 0 | J109: =+J79+J108 -> 0 | K109: =+K79+K108 -> 0 | L109: =+L79+L108 -> 0
A111: =+Grunddaten!B35 -> Bank 4 | E111: Konto-Nr.
D113: Saldo zum Tagesbeginn | E113: 0 | F113: =+E143 -> 0 | G113: =+F143 -> 0 | H113: =+G143 -> 0 | I113: =+H143 -> 0 | J113: =+I143 -> 0 | K113: =+J143 -> 0 | L113: =+K143 -> 0
A114: Einnahmen
B124: Geldverkehr
D125: Summe Einnahmen | E125: =SUM(E114:E124) -> 0 | F125: =SUM(F114:F124) -> 0 | G125: =SUM(G114:G124) -> 0 | H125: =SUM(H114:H124) -> 0 | I125: =SUM(I114:I124) -> 0 | J125: =SUM(J114:J124) -> 0 | K125: =SUM(K114:K124) -> 0 | L125: =SUM(L114:L124) -> 0
A126: Ausgaben
B140: Geldverkehr
D141: Summe Ausgaben | E141: =SUM(E127:E140) -> 0 | F141: =SUM(F127:F140) -> 0 | G141: =SUM(G127:G140) -> 0 | H141: =SUM(H127:H140) -> 0 | I141: =SUM(I127:I140) -> 0 | J141: =SUM(J127:J140) -> 0 | K141: =SUM(K127:K140) -> 0 | L141: =SUM(L127:L140) -> 0
D142: Saldo Einnahmen ./. Ausgaben | E142: =+E125-E141 -> 0 | F142: =+F125-F141 -> 0 | G142: =+G125-G141 -> 0 | H142: =+H125-H141 -> 0 | I142: =+I125-I141 -> 0 | J142: =+J125-J141 -> 0 | K142: =+K125-K141 -> 0 | L142: =+L125-L141 -> 0
D143: Tagesendsaldo | E143: =+E113+E142 -> 0 | F143: =+F113+F142 -> 0 | G143: =+G113+G142 -> 0 | H143: =+H113+H142 -> 0 | I143: =+I113+I142 -> 0 | J143: =+J113+J142 -> 0 | K143: =+K113+K142 -> 0 | L143: =+L113+L142 -> 0
A145: =+Grunddaten!B36 -> Bank 5 | E145: Konto-Nr. | F145: =+Grunddaten!D36 -> 0
D147: Saldo zum Tagesbeginn | E147: 1.6 | F147: =+E177 -> 2.220446e-15 | G147: =+F177 -> 14.6 | H147: =+G177 -> 15.5 | I147: =+H177 -> 5.5 | J147: =+I177 -> 0.5 | K147: =+J177 -> 0.5 | L147: =+K177 -> 0.5
A148: Einnahmen
B149: Debitoren | F149: 14.6 | G149: 21.3 | H149: 10 | I149: 10 | L149: 20
B150: Kasse
B151: Einfinanzierungen
B152: Händlerkonto
B153: Prämien VIPS
B158: Geldverkehr | E158: 20.6
D159: Summe Einnahmen | E159: =SUM(E148:E158) -> 20.6 | F159: =SUM(F148:F158) -> 14.6 | G159: =SUM(G148:G158) -> 21.3 | H159: =SUM(H148:H158) -> 10 | I159: =SUM(I148:I158) -> 10 | J159: =SUM(J148:J158) -> 0 | K159: =SUM(K148:K158) -> 0 | L159: =SUM(L148:L158) -> 20
A160: Ausgaben
B161: Lohn/Gehalt
B162: Lohnsteuer
B163: Sozialversicherung
B164: Mieten
B165: Ablös. Fahrzeuge | E165: 22.2 | G165: 20.4 | H165: 20 | I165: 15 | L165: 20
B166: Zahlung Kreditoren
B167: Zinsen/
B168: Europa S. Ablös.MWST
B169: Händlerkonto
B170: Tilgung
B171: Kred. Verb.
B174: Geldverkehr
D175: Summe Ausgaben | E175: =SUM(E161:E174) -> 22.2 | F175: =SUM(F161:F174) -> 0 | G175: =SUM(G161:G174) -> 20.4 | H175: =SUM(H161:H174) -> 20 | I175: =SUM(I161:I174) -> 15 | J175: =SUM(J161:J174) -> 0 | K175: =SUM(K161:K174) -> 0 | L175: =SUM(L161:L174) -> 20
D176: Saldo Einnahmen ./. Ausgaben | E176: =+E159-E175 -> -1.6 | F176: =+F159-F175 -> 14.6 | G176: =+G159-G175 -> 0.9 | H176: =+H159-H175 -> -10 | I176: =+I159-I175 -> -5 | J176: =+J159-J175 -> 0 | K176: =+K159-K175 -> 0 | L176: =+L159-L175 -> 0
D177: Tagesendsaldo | E177: =+E147+E176 -> 2.220446e-15 | F177: =+F147+F176 -> 14.6 | G177: =+G147+G176 -> 15.5 | H177: =+H147+H176 -> 5.5 | I177: =+I147+I176 -> 0.5 | J177: =+J147+J176 -> 0.5 | K177: =+K147+K176 -> 0.5 | L177: =+L147+L176 -> 0.5
...

Sheet Standort 4
A1: Standort 4 | I1: geplant
J2: Name | K2: Datum
A3: Liquiditätsplanung aufgrund der Einzelkonten
A4: Planung in T€
E5: =+Holding!E5 -> Montag | F5: =+Holding!F5 -> Dienstag | G5: =+Holding!G5 -> Mittwoch | H5: =+Holding!H5 -> Donnerstag | I5: =+Holding!I5 -> Freitag | J5: =+Holding!J5 -> Samstag | K5: =+Holding!K5 -> Sonntag | L5: =+Holding!L5 -> Montag
E6: 45870 | F6: =+E6+1 -> 45871 | G6: =+F6+1 -> 45872 | H6: =+G6+1 -> 45873 | I6: =+H6+1 -> 45874 | J6: =+I6+1 -> 45875 | K6: =+J6+1 -> 45876 | L6: =+K6+1 -> 45877
D7: Text | E7: T€ | F7: T€ | G7: T€ | H7: T€ | I7: T€ | J7: T€ | K7: T€ | L7: T€
A8: =+Grunddaten!B44 -> Bank 1 | E8: Konto-Nr. | F8: =+Grunddaten!D44 -> 0
D10: Saldo zum Tagesbeginn | E10: -499.2 | F10: =+E41 -> -519.2 | G10: =+F41 -> -535.9 | H10: =+G41 -> -531.4 | I10: =+H41 -> -536.8 | J10: =+I41 -> -540.8 | K10: =+J41 -> -540.8 | L10: =+K41 -> -540.8
A11: Einnahmen
B13: Debitoren | E13: 4.5 | F13: 4.5 | G13: 4.5 | H13: 4.5 | I13: 4.5 | L13: 4.5
B14: Kassen | F14: 3 | L14: 10.5
B15: GW Finanzierungen
B16: Volvo Autobank
B21: Geldverkehr
D22: Summe Einnahmen | E22: =SUM(E11:E21) -> 4.5 | F22: =SUM(F11:F21) -> 7.5 | G22: =SUM(G11:G21) -> 4.5 | H22: =SUM(H11:H21) -> 4.5 | I22: =SUM(I11:I21) -> 4.5 | J22: =SUM(J11:J21) -> 0 | K22: =SUM(K11:K21) -> 0 | L22: =SUM(L11:L21) -> 15
A23: Ausgaben
B24: Löhne/Gehälter
B25: Lohnsteuer | E25: 3.1
B26: Sozialversicherung | E26: 2.4
B27: Kreditoren | H27: 5
B28: Abbuchung Teile Rg. Volvo | F28: 4.7 | I28: 5.3
B29: Tilgung Fahrzeugfinanzierungen | E29: 6.7 | F29: 17.8 | H29: 4.9 | I29: 3.2 | L29: 9.4
B30: Löhne/Gehälter
B31: Ablösung Fahrzeuge | E31: 12.3 | F31: 1.7
B32: Miete
B33: UST
B34: Zinsen Volvo Autobank
B38: Geldverkehr
D39: Summe Ausgaben | E39: =SUM(E24:E38) -> 24.5 | F39: =SUM(F24:F38) -> 24.2 | G39: =SUM(G24:G38) -> 0 | H39: =SUM(H24:H38) -> 9.9 | I39: =SUM(I24:I38) -> 8.5 | J39: =SUM(J24:J38) -> 0 | K39: =SUM(K24:K38) -> 0 | L39: =SUM(L24:L38) -> 9.4
D40: Saldo Einnahmen ./. Ausgaben | E40: =+E22-E39 -> -20 | F40: =+F22-F39 -> -16.7 | G40: =+G22-G39 -> 4.5 | H40: =+H22-H39 -> -5.4 | I40: =+I22-I39 -> -4 | J40: =+J22-J39 -> 0 | K40: =+K22-K39 -> 0 | L40: =+L22-L39 -> 5.6
D41: Tagesendsaldo | E41: =+E10+E40 -> -519.2 | F41: =+F10+F40 -> -535.9 | G41: =+G10+G40 -> -531.4 | H41: =+H10+H40 -> -536.8 | I41: =+I10+I40 -> -540.8 | J41: =+J10+J40 -> -540.8 | K41: =+K10+K40 -> -540.8 | L41: =+L10+L40 -> -535.2
A43: =+Grunddaten!B45 -> Bank 2 | E43: Konto-Nr. | F43: =+Grunddaten!D45 -> 0
D45: Saldo zum Tagesbeginn | F45: =E75 -> 0 | G45: =F75 -> 0 | H45: =G75 -> 0 | I45: =H75 -> 0 | J45: =I75 -> 0 | K45: =J75 -> 0 | L45: =K75 -> 0
A46: Einnahmen
B55: Geldverkehr
D56: Summe Einnahmen | E56: =SUM(E46:E55) -> 0 | F56: =SUM(F46:F55) -> 0 | G56: =SUM(G46:G55) -> 0 | H56: =SUM(H46:H55) -> 0 | I56: =SUM(I46:I55) -> 0 | J56: =SUM(J46:J55) -> 0 | K56: =SUM(K46:K55) -> 0 | L56: =SUM(L46:L55) -> 0
A57: Ausgaben
B72: Geldverkehr
D73: Summe Ausgaben | E73: =SUM(E58:E72) -> 0 | F73: =SUM(F58:F72) -> 0 | G73: =SUM(G58:G72) -> 0 | H73: =SUM(H58:H72) -> 0 | I73: =SUM(I58:I72) -> 0 | J73: =SUM(J58:J72) -> 0 | K73: =SUM(K58:K72) -> 0 | L73: =SUM(L58:L72) -> 0
D74: Saldo Einnahmen ./. Ausgaben | E74: =+E56-E73 -> 0 | F74: =+F56-F73 -> 0 | G74: =+G56-G73 -> 0 | H74: =+H56-H73 -> 0 | I74: =+I56-I73 -> 0 | J74: =+J56-J73 -> 0 | K74: =+K56-K73 -> 0 | L74: =+L56-L73 -> 0
D75: Tagesendsaldo | E75: =+E45+E74 -> 0 | F75: =+F45+F74 -> 0 | G75: =+G45+G74 -> 0 | H75: =+H45+H74 -> 0 | I75: =+I45+I74 -> 0 | J75: =+J45+J74 -> 0 | K75: =+K45+K74 -> 0 | L75: =+L45+L74 -> 0
A77: =+Grunddaten!B46 -> Bank 3 | E77: Konto-Nr. | F77: =+Grunddaten!D46 -> 0
D79: Saldo zum Tagesbeginn | E79: 0 | F79: =+E109 -> 0 | G79: =+F109 -> 0 | H79: =+G109 -> 0 | I79: =+H109 -> 0 | J79: =+I109 -> 0 | K79: =+J109 -> 0 | L79: =+K109 -> 0
A80: Einnahmen
B90: Geldverkehr
D91: Summe Einnahmen | E91: =SUM(E80:E90) -> 0 | F91: =SUM(F80:F90) -> 0 | G91: =SUM(G80:G90) -> 0 | H91: =SUM(H80:H90) -> 0 | I91: =SUM(I80:I90) -> 0 | J91: =SUM(J80:J90) -> 0 | K91: =SUM(K80:K90) -> 0 | L91: =SUM(L80:L90) -> 0
A92: Ausgaben
B106: Geldverkehr
D107: Summe Ausgaben | E107: =SUM(E93:E106) -> 0 | F107: =SUM(F93:F106) -> 0 | G107: =SUM(G93:G106) -> 0 | H107: =SUM(H93:H106) -> 0 | I107: =SUM(I93:I106) -> 0 | J107: =SUM(J93:J106) -> 0 | K107: =SUM(K93:K106) -> 0 | L107: =SUM(L93:L106) -> 0
D108: Saldo Einnahmen ./. Ausgaben | E108: =+E91-E107 -> 0 | F108: =+F91-F107 -> 0 | G108: =+G91-G107 -> 0 | H108: =+H91-H107 -> 0 | I108: =+I91-I107 -> 0 | J108: =+J91-J107 -> 0 | K108: =+K91-K107 -> 0 | L108: =+L91-L107 -> 0
D109: Tagesendsaldo | E109: =+E79+E108 -> 0 | F109: =+F79+F108 -> 0 | G109: =+G79+G108 -> 0 | H109: =+H79+H108 -> 0 | I109: =+I79+I108 -> 0 | J109: =+J79+J108 -> 0 | K109: =+K79+K108 -> 0 | L109: =+L79+L108 -> 0
A111: =+Grunddaten!B47 -> Bank 4 | E111: Konto-Nr. | F111: =+Grunddaten!D47 -> 0
D113: Saldo zum Tagesbeginn | E113: 0 | F113: =+E143 -> 0 | G113: =+F143 -> 0 | H113: =+G143 -> 0 | I113: =+H143 -> 0 | J113: =+I143 -> 0 | K113: =+J143 -> 0 | L113: =+K143 -> 0
A114: Einnahmen
B124: Geldverkehr
D125: Summe Einnahmen | E125: =SUM(E114:E124) -> 0 | F125: =SUM(F114:F124) -> 0 | G125: =SUM(G114:G124) -> 0 | H125: =SUM(H114:H124) -> 0 | I125: =SUM(I114:I124) -> 0 | J125: =SUM(J114:J124) -> 0 | K125: =SUM(K114:K124) -> 0 | L125: =SUM(L114:L124) -> 0
A126: Ausgaben
B140: Geldverkehr
D141: Summe Ausgaben | E141: =SUM(E127:E140) -> 0 | F141: =SUM(F127:F140) -> 0 | G141: =SUM(G127:G140) -> 0 | H141: =SUM(H127:H140) -> 0 | I141: =SUM(I127:I140) -> 0 | J141: =SUM(J127:J140) -> 0 | K141: =SUM(K127:K140) -> 0 | L141: =SUM(L127:L140) -> 0
D142: Saldo Einnahmen ./. Ausgaben | E142: =+E125-E141 -> 0 | F142: =+F125-F141 -> 0 | G142: =+G125-G141 -> 0 | H142: =+H125-H141 -> 0 | I142: =+I125-I141 -> 0 | J142: =+J125-J141 -> 0 | K142: =+K125-K141 -> 0 | L142: =+L125-L141 -> 0
D143: Tagesendsaldo | E143: =+E113+E142 -> 0 | F143: =+F113+F142 -> 0 | G143: =+G113+G142 -> 0 | H143: =+H113+H142 -> 0 | I143: =+I113+I142 -> 0 | J143: =+J113+J142 -> 0 | K143: =+K113+K142 -> 0 | L143: =+L113+L142 -> 0
A145: =+Grunddaten!B48 -> Bank 5 | E145: Konto-Nr. | F145: =+Grunddaten!D48 -> 0
D147: Saldo zum Tagesbeginn | E147: 0 | F147: =+E177 -> 0 | G147: =+F177 -> 0 | H147: =+G177 -> 0 | I147: =+H177 -> 0 | J147: =+I177 -> 0 | K147: =+J177 -> 0 | L147: =+K177 -> 0
A148: Einnahmen
B158: Geldverkehr
D159: Summe Einnahmen | E159: =SUM(E148:E158) -> 0 | F159: =SUM(F148:F158) -> 0 | G159: =SUM(G148:G158) -> 0 | H159: =SUM(H148:H158) -> 0 | I159: =SUM(I148:I158) -> 0 | J159: =SUM(J148:J158) -> 0 | K159: =SUM(K148:K158) -> 0 | L159: =SUM(L148:L158) -> 0
A160: Ausgaben
B174: Geldverkehr
D175: Summe Ausgaben | E175: =SUM(E161:E174) -> 0 | F175: =SUM(F161:F174) -> 0 | G175: =SUM(G161:G174) -> 0 | H175: =SUM(H161:H174) -> 0 | I175: =SUM(I161:I174) -> 0 | J175: =SUM(J161:J174) -> 0 | K175: =SUM(K161:K174) -> 0 | L175: =SUM(L161:L174) -> 0
D176: Saldo Einnahmen ./. Ausgaben | E176: =+E159-E175 -> 0 | F176: =+F159-F175 -> 0 | G176: =+G159-G175 -> 0 | H176: =+H159-H175 -> 0 | I176: =+I159-I175 -> 0 | J176: =+J159-J175 -> 0 | K176: =+K159-K175 -> 0 | L176: =+L159-L175 -> 0
D177: Tagesendsaldo | E177: =+E147-E176 -> 0 | F177: =+F147-F176 -> 0 | G177: =+G147-G176 -> 0 | H177: =+H147-H176 -> 0 | I177: =+I147-I176 -> 0 | J177: =+J147-J176 -> 0 | K177: =+K147-K176 -> 0 | L177: =+L147-L176 -> 0
A179: =Grunddaten!B49 -> Bank 6 | E179: Konto-Nr. | F179: =+Grunddaten!D49 -> 0
D181: Saldo zum Tagesbeginn | F181: =+E211 -> 0 | G181: =+F211 -> 0 | H181: =+G211 -> 0 | I181: =+H211 -> 0 | J181: =+I211 -> 0 | K181: =+J211 -> 0 | L181: =+K211 -> 0
A182: Einnahmen
B192: Geldverkehr
D193: Summe Einnahmen | E193: =SUM(E182:E192) -> 0 | F193: =SUM(F182:F192) -> 0 | G193: =SUM(G182:G192) -> 0 | H193: =SUM(H182:H192) -> 0 | I193: =SUM(I182:I192) -> 0 | J193: =SUM(J182:J192) -> 0 | K193: =SUM(K182:K192) -> 0 | L193: =SUM(L182:L192) -> 0
A194: Ausgaben
B208: Geldverkehr
D209: Summe Ausgaben | E209: =SUM(E195:E208) -> 0 | F209: =SUM(F195:F208) -> 0 | G209: =SUM(G195:G208) -> 0 | H209: =SUM(H195:H208) -> 0 | I209: =SUM(I195:I208) -> 0 | J209: =SUM(J195:J208) -> 0 | K209: =SUM(K195:K208) -> 0 | L209: =SUM(L195:L208) -> 0
D210: Saldo Einnahmen ./. Ausgaben | E210: =+E193-E209 -> 0 | F210: =+F193-F209 -> 0 | G210: =+G193-G209 -> 0 | H210: =+H193-H209 -> 0 | I210: =+I193-I209 -> 0 | J210: =+J193-J209 -> 0 | K210: =+K193-K209 -> 0 | L210: =+L193-L209 -> 0
D211: Tagesendsaldo | E211: =+E181+E210 -> 0 | F211: =+F181+F210 -> 0 | G211: =+G181+G210 -> 0 | H211: =+H181+H210 -> 0 | I211: =+I181+I210 -> 0 | J211: =+J181+J210 -> 0 | K211: =+K181+K210 -> 0 | L211: =+L181+L210 -> 0
A213: =Grunddaten!B50 -> Bank 7 | E213: Konto-Nr. | F213: =+Grunddaten!D50 -> 0
D215: Saldo zum Tagesbeginn | F215: =+E245 -> 0 | G215: =+F245 -> 0 | H215: =+G245 -> 0 | I215: =+H245 -> 0 | J215: =+I245 -> 0 | K215: =+J245 -> 0 | L215: =+K245 -> 0
A216: Einnahmen
B226: Geldverkehr
D227: Summe Einnahmen | E227: =SUM(E216:E226) -> 0 | F227: =SUM(F216:F226) -> 0 | G227: =SUM(G216:G226) -> 0 | H227: =SUM(H216:H226) -> 0 | I227: =SUM(I216:I226) -> 0 | J227: =SUM(J216:J226) -> 0 | K227: =SUM(K216:K226) -> 0 | L227: =SUM(L216:L226) -> 0
A228: Ausgaben
B242: Geldverkehr
D243: Summe Ausgaben | E243: =SUM(E229:E242) -> 0 | F243: =SUM(F229:F242) -> 0 | G243: =SUM(G229:G242) -> 0 | H243: =SUM(H229:H242) -> 0 | I243: =SUM(I229:I242) -> 0 | J243: =SUM(J229:J242) -> 0 | K243: =SUM(K229:K242) -> 0 | L243: =SUM(L229:L242) -> 0
D244: Saldo Einnahmen ./. Ausgaben | E244: =+E227-E243 -> 0 | F244: =+F227-F243 -> 0 | G244: =+G227-G243 -> 0 | H244: =+H227-H243 -> 0 | I244: =+I227-I243 -> 0 | J244: =+J227-J243 -> 0 | K244: =+K227-K243 -> 0 | L244: =+L227-L243 -> 0
D245: Tagesendsaldo | E245: =+E215+E244 -> 0 | F245: =+F215+F244 -> 0 | G245: =+G215+G244 -> 0 | H245: =+H215+H244 -> 0 | I245: =+I215+I244 -> 0 | J245: =+J215+J244 -> 0 | K245: =+K215+K244 -> 0 | L245: =+L215+L244 -> 0
A247: =Grunddaten!B51 -> Bank 8 | E247: Konto-Nr. | F247: =+Grunddaten!D51 -> 0
D249: Saldo zum Tagesbeginn | F249: =+E279 -> 0 | G249: =+F279 -> 0 | H249: =+G279 -> 0 | I249: =+H279 -> 0 | J249: =+I279 -> 0 | K249: =+J279 -> 0 | L249: =+K279 -> 0
A250: Einnahmen
B260: Geldverkehr
D261: Summe Einnahmen | E261: =SUM(E250:E260) -> 0 | F261: =SUM(F250:F260) -> 0 | G261: =SUM(G250:G260) -> 0 | H261: =SUM(H250:H260) -> 0 | I261: =SUM(I250:I260) -> 0 | J261: =SUM(J250:J260) -> 0 | K261: =SUM(K250:K260) -> 0 | L261: =SUM(L250:L260) -> 0
A262: Ausgaben
B276: Geldverkehr
D277: Summe Ausgaben | E277: =SUM(E263:E276) -> 0 | F277: =SUM(F263:F276) -> 0 | G277: =SUM(G263:G276) -> 0 | H277: =SUM(H263:H276) -> 0 | I277: =SUM(I263:I276) -> 0 | J277: =SUM(J263:J276) -> 0 | K277: =SUM(K263:K276) -> 0 | L277: =SUM(L263:L276) -> 0
...

Sheet Holding
A1: Holding | I1: geplant
J2: Name | K2: Datum
A3: Liquiditätsplanung aufgrund der Einzelkonten
A4: Planung in T€
E5: Montag | F5: Dienstag | G5: Mittwoch | H5: Donnerstag | I5: Freitag | J5: Samstag | K5: Sonntag | L5: Montag
E6: 45870 | F6: =+E6+1 -> 45871 | G6: =+F6+1 -> 45872 | H6: =+G6+1 -> 45873 | I6: =+H6+1 -> 45874 | J6: =+I6+1 -> 45875 | K6: =+J6+1 -> 45876 | L6: =+K6+1 -> 45877
D7: Text | E7: T€ | F7: T€ | G7: T€ | H7: T€ | I7: T€ | J7: T€ | K7: T€ | L7: T€
A8: =+Grunddaten!B56 -> Bank 1 | E8: Konto-Nr. | F8: =+Grunddaten!D56 -> 0
D10: Saldo zum Tagesbeginn | E10: -457.9 | F10: =+E41 -> -444.5 | G10: =+F41 -> -444.1 | H10: =+G41 -> -444.1 | I10: =+H41 -> -442.6 | J10: =+I41 -> -439.6 | K10: =+J41 -> -439.6 | L10: =+K41 -> -439.6
A11: Einnahmen
B13: xxxx
B14: verbundene Unternehmen | E14: 3.6 | F14: 0.4 | G14: 2.3 | H14: 2 | I14: 3 | L14: 4.4
B15: xxxx | E15: 9.8
B16: Gew./Kö.St. L
B17: xxxx
B18: xxxx
B21: Geldverkehr
D22: Summe Einnahmen | E22: =SUM(E11:E21) -> 13.4 | F22: =SUM(F11:F21) -> 0.4 | G22: =SUM(G11:G21) -> 2.3 | H22: =SUM(H11:H21) -> 2 | I22: =SUM(I11:I21) -> 3 | J22: =SUM(J11:J21) -> 0 | K22: =SUM(K11:K21) -> 0 | L22: =SUM(L11:L21) -> 4.4
A23: Ausgaben
B25: Zlg. Kreditoren | G25: 2.3 | H25: 0.5
B26: Zlg. Verbundene Unternehmen
B27: Geldverkehr
B28: Office ED | L28: 6.8
B29: xxxxx
B30: xxxx
B31: Zinsen/Tilgung Banken
B32: Grundbesitzabgaben
B33: Sozialversicherung
D39: Summe Ausgaben | E39: =SUM(E24:E38) -> 0 | F39: =SUM(F24:F38) -> 0 | G39: =SUM(G24:G38) -> 2.3 | H39: =SUM(H24:H38) -> 0.5 | I39: =SUM(I24:I38) -> 0 | J39: =SUM(J24:J38) -> 0 | K39: =SUM(K24:K38) -> 0 | L39: =SUM(L24:L38) -> 6.8
D40: Saldo Einnahmen ./. Ausgaben | E40: =+E22-E39 -> 13.4 | F40: =+F22-F39 -> 0.4 | G40: =+G22-G39 -> 0 | H40: =+H22-H39 -> 1.5 | I40: =+I22-I39 -> 3 | J40: =+J22-J39 -> 0 | K40: =+K22-K39 -> 0 | L40: =+L22-L39 -> -2.4
D41: Tagesendsaldo | E41: =+E10+E40 -> -444.5 | F41: =+F10+F40 -> -444.1 | G41: =+G10+G40 -> -444.1 | H41: =+H10+H40 -> -442.6 | I41: =+I10+I40 -> -439.6 | J41: =+J10+J40 -> -439.6 | K41: =+K10+K40 -> -439.6 | L41: =+L10+L40 -> -442
A43: =+Grunddaten!B57 -> Bank 2 | E43: Konto-Nr. | F43: =+Grunddaten!D57 -> 0
D45: Saldo zum Tagesbeginn | F45: =E75 -> 0 | G45: =F75 -> 0 | H45: =G75 -> 0 | I45: =H75 -> 0 | J45: =I75 -> 0 | K45: =J75 -> 0 | L45: =K75 -> 0
A46: Einnahmen
B55: Geldverkehr
D56: Summe Einnahmen | E56: =SUM(E46:E55) -> 0 | F56: =SUM(F46:F55) -> 0 | G56: =SUM(G46:G55) -> 0 | H56: =SUM(H46:H55) -> 0 | I56: =SUM(I46:I55) -> 0 | J56: =SUM(J46:J55) -> 0 | K56: =SUM(K46:K55) -> 0 | L56: =SUM(L46:L55) -> 0
A57: Ausgaben
B72: Geldverkehr
D73: Summe Ausgaben | E73: =SUM(E58:E72) -> 0 | F73: =SUM(F58:F72) -> 0 | G73: =SUM(G58:G72) -> 0 | H73: =SUM(H58:H72) -> 0 | I73: =SUM(I58:I72) -> 0 | J73: =SUM(J58:J72) -> 0 | K73: =SUM(K58:K72) -> 0 | L73: =SUM(L58:L72) -> 0
D74: Saldo Einnahmen ./. Ausgaben | E74: =+E56-E73 -> 0 | F74: =+F56-F73 -> 0 | G74: =+G56-G73 -> 0 | H74: =+H56-H73 -> 0 | I74: =+I56-I73 -> 0 | J74: =+J56-J73 -> 0 | K74: =+K56-K73 -> 0 | L74: =+L56-L73 -> 0
D75: Tagesendsaldo | E75: =+E45+E74 -> 0 | F75: =+F45+F74 -> 0 | G75: =+G45+G74 -> 0 | H75: =+H45+H74 -> 0 | I75: =+I45+I74 -> 0 | J75: =+J45+J74 -> 0 | K75: =+K45+K74 -> 0 | L75: =+L45+L74 -> 0
A77: =+Grunddaten!B58 -> Bank 3 | E77: Konto-Nr. | F77: =+Grunddaten!D58 -> 0
D79: Saldo zum Tagesbeginn | E79: 0 | F79: =+E109 -> 0 | G79: =+F109 -> 0 | H79: =+G109 -> 0 | I79: =+H109 -> 0 | J79: =+I109 -> 0 | K79: =+J109 -> 0 | L79: =+K109 -> 0
A80: Einnahmen
B90: Geldverkehr
D91: Summe Einnahmen | E91: =SUM(E80:E90) -> 0 | F91: =SUM(F80:F90) -> 0 | G91: =SUM(G80:G90) -> 0 | H91: =SUM(H80:H90) -> 0 | I91: =SUM(I80:I90) -> 0 | J91: =SUM(J80:J90) -> 0 | K91: =SUM(K80:K90) -> 0 | L91: =SUM(L80:L90) -> 0
A92: Ausgaben
B106: Geldverkehr
D107: Summe Ausgaben | E107: =SUM(E93:E106) -> 0 | F107: =SUM(F93:F106) -> 0 | G107: =SUM(G93:G106) -> 0 | H107: =SUM(H93:H106) -> 0 | I107: =SUM(I93:I106) -> 0 | J107: =SUM(J93:J106) -> 0 | K107: =SUM(K93:K106) -> 0 | L107: =SUM(L93:L106) -> 0
D108: Saldo Einnahmen ./. Ausgaben | E108: =+E91-E107 -> 0 | F108: =+F91-F107 -> 0 | G108: =+G91-G107 -> 0 | H108: =+H91-H107 -> 0 | I108: =+I91-I107 -> 0 | J108: =+J91-J107 -> 0 | K108: =+K91-K107 -> 0 | L108: =+L91-L107 -> 0
D109: Tagesendsaldo | E109: =+E79+E108 -> 0 | F109: =+F79+F108 -> 0 | G109: =+G79+G108 -> 0 | H109: =+H79+H108 -> 0 | I109: =+I79+I108 -> 0 | J109: =+J79+J108 -> 0 | K109: =+K79+K108 -> 0 | L109: =+L79+L108 -> 0
A111: =+Grunddaten!B59 -> Bank 4 | E111: Konto-Nr. | F111: =+Grunddaten!D59 -> 0
D113: Saldo zum Tagesbeginn | E113: 0 | F113: =+E143 -> 0 | G113: =+F143 -> 0 | H113: =+G143 -> 0 | I113: =+H143 -> 0 | J113: =+I143 -> 0 | K113: =+J143 -> 0 | L113: =+K143 -> 0
A114: Einnahmen
B124: Geldverkehr
D125: Summe Einnahmen | E125: =SUM(E114:E124) -> 0 | F125: =SUM(F114:F124) -> 0 | G125: =SUM(G114:G124) -> 0 | H125: =SUM(H114:H124) -> 0 | I125: =SUM(I114:I124) -> 0 | J125: =SUM(J114:J124) -> 0 | K125: =SUM(K114:K124) -> 0 | L125: =SUM(L114:L124) -> 0
A126: Ausgaben
B140: Geldverkehr
D141: Summe Ausgaben | E141: =SUM(E127:E140) -> 0 | F141: =SUM(F127:F140) -> 0 | G141: =SUM(G127:G140) -> 0 | H141: =SUM(H127:H140) -> 0 | I141: =SUM(I127:I140) -> 0 | J141: =SUM(J127:J140) -> 0 | K141: =SUM(K127:K140) -> 0 | L141: =SUM(L127:L140) -> 0
D142: Saldo Einnahmen ./. Ausgaben | E142: =+E125-E141 -> 0 | F142: =+F125-F141 -> 0 | G142: =+G125-G141 -> 0 | H142: =+H125-H141 -> 0 | I142: =+I125-I141 -> 0 | J142: =+J125-J141 -> 0 | K142: =+K125-K141 -> 0 | L142: =+L125-L141 -> 0
D143: Tagesendsaldo | E143: =+E113+E142 -> 0 | F143: =+F113+F142 -> 0 | G143: =+G113+G142 -> 0 | H143: =+H113+H142 -> 0 | I143: =+I113+I142 -> 0 | J143: =+J113+J142 -> 0 | K143: =+K113+K142 -> 0 | L143: =+L113+L142 -> 0
A145: =+Grunddaten!B60 -> Bank 5 | E145: Konto-Nr. | F145: =+Grunddaten!D60 -> 0
D147: Saldo zum Tagesbeginn | E147: 0 | F147: =+E177 -> 0 | G147: =+F177 -> 0 | H147: =+G177 -> 0 | I147: =+H177 -> 0 | J147: =+I177 -> 0 | K147: =+J177 -> 0 | L147: =+K177 -> 0
A148: Einnahmen
B158: Geldverkehr
D159: Summe Einnahmen | E159: =SUM(E148:E158) -> 0 | F159: =SUM(F148:F158) -> 0 | G159: =SUM(G148:G158) -> 0 | H159: =SUM(H148:H158) -> 0 | I159: =SUM(I148:I158) -> 0 | J159: =SUM(J148:J158) -> 0 | K159: =SUM(K148:K158) -> 0 | L159: =SUM(L148:L158) -> 0
A160: Ausgaben
B174: Geldverkehr
D175: Summe Ausgaben | E175: =SUM(E161:E174) -> 0 | F175: =SUM(F161:F174) -> 0 | G175: =SUM(G161:G174) -> 0 | H175: =SUM(H161:H174) -> 0 | I175: =SUM(I161:I174) -> 0 | J175: =SUM(J161:J174) -> 0 | K175: =SUM(K161:K174) -> 0 | L175: =SUM(L161:L174) -> 0
D176: Saldo Einnahmen ./. Ausgaben | E176: =+E159-E175 -> 0 | F176: =+F159-F175 -> 0 | G176: =+G159-G175 -> 0 | H176: =+H159-H175 -> 0 | I176: =+I159-I175 -> 0 | J176: =+J159-J175 -> 0 | K176: =+K159-K175 -> 0 | L176: =+L159-L175 -> 0
D177: Tagesendsaldo | E177: =+E147-E176 -> 0 | F177: =+F147-F176 -> 0 | G177: =+G147-G176 -> 0 | H177: =+H147-H176 -> 0 | I177: =+I147-I176 -> 0 | J177: =+J147-J176 -> 0 | K177: =+K147-K176 -> 0 | L177: =+L147-L176 -> 0
A179: =Grunddaten!B61 -> Bank 6 | E179: Konto-Nr. | F179: =+Grunddaten!D61 -> 0
D181: Saldo zum Tagesbeginn | F181: =+E211 -> 0 | G181: =+F211 -> 0 | H181: =+G211 -> 0 | I181: =+H211 -> 0 | J181: =+I211 -> 0 | K181: =+J211 -> 0 | L181: =+K211 -> 0
A182: Einnahmen
B192: Geldverkehr
D193: Summe Einnahmen | E193: =SUM(E182:E192) -> 0 | F193: =SUM(F182:F192) -> 0 | G193: =SUM(G182:G192) -> 0 | H193: =SUM(H182:H192) -> 0 | I193: =SUM(I182:I192) -> 0 | J193: =SUM(J182:J192) -> 0 | K193: =SUM(K182:K192) -> 0 | L193: =SUM(L182:L192) -> 0
A194: Ausgaben
B208: Geldverkehr
D209: Summe Ausgaben | E209: =SUM(E195:E208) -> 0 | F209: =SUM(F195:F208) -> 0 | G209: =SUM(G195:G208) -> 0 | H209: =SUM(H195:H208) -> 0 | I209: =SUM(I195:I208) -> 0 | J209: =SUM(J195:J208) -> 0 | K209: =SUM(K195:K208) -> 0 | L209: =SUM(L195:L208) -> 0
D210: Saldo Einnahmen ./. Ausgaben | E210: =+E193-E209 -> 0 | F210: =+F193-F209 -> 0 | G210: =+G193-G209 -> 0 | H210: =+H193-H209 -> 0 | I210: =+I193-I209 -> 0 | J210: =+J193-J209 -> 0 | K210: =+K193-K209 -> 0 | L210: =+L193-L209 -> 0
D211: Tagesendsaldo | E211: =+E181+E210 -> 0 | F211: =+F181+F210 -> 0 | G211: =+G181+G210 -> 0 | H211: =+H181+H210 -> 0 | I211: =+I181+I210 -> 0 | J211: =+J181+J210 -> 0 | K211: =+K181+K210 -> 0 | L211: =+L181+L210 -> 0
A213: =Grunddaten!B62 -> Bank 7 | E213: Konto-Nr. | F213: =+Grunddaten!D62 -> 0
D215: Saldo zum Tagesbeginn | F215: =+E245 -> 0 | G215: =+F245 -> 0 | H215: =+G245 -> 0 | I215: =+H245 -> 0 | J215: =+I245 -> 0 | K215: =+J245 -> 0 | L215: =+K245 -> 0
A216: Einnahmen
B226: Geldverkehr
D227: Summe Einnahmen | E227: =SUM(E216:E226) -> 0 | F227: =SUM(F216:F226) -> 0 | G227: =SUM(G216:G226) -> 0 | H227: =SUM(H216:H226) -> 0 | I227: =SUM(I216:I226) -> 0 | J227: =SUM(J216:J226) -> 0 | K227: =SUM(K216:K226) -> 0 | L227: =SUM(L216:L226) -> 0
A228: Ausgaben
B242: Geldverkehr
D243: Summe Ausgaben | E243: =SUM(E229:E242) -> 0 | F243: =SUM(F229:F242) -> 0 | G243: =SUM(G229:G242) -> 0 | H243: =SUM(H229:H242) -> 0 | I243: =SUM(I229:I242) -> 0 | J243: =SUM(J229:J242) -> 0 | K243: =SUM(K229:K242) -> 0 | L243: =SUM(L229:L242) -> 0
D244: Saldo Einnahmen ./. Ausgaben | E244: =+E227-E243 -> 0 | F244: =+F227-F243 -> 0 | G244: =+G227-G243 -> 0 | H244: =+H227-H243 -> 0 | I244: =+I227-I243 -> 0 | J244: =+J227-J243 -> 0 | K244: =+K227-K243 -> 0 | L244: =+L227-L243 -> 0
D245: Tagesendsaldo | E245: =+E215+E244 -> 0 | F245: =+F215+F244 -> 0 | G245: =+G215+G244 -> 0 | H245: =+H215+H244 -> 0 | I245: =+I215+I244 -> 0 | J245: =+J215+J244 -> 0 | K245: =+K215+K244 -> 0 | L245: =+L215+L244 -> 0
A247: =Grunddaten!B63 -> Bank 8 | E247: Konto-Nr. | F247: =+Grunddaten!D63 -> 0
D249: Saldo zum Tagesbeginn | F249: =+E279 -> 0 | G249: =+F279 -> 0 | H249: =+G279 -> 0 | I249: =+H279 -> 0 | J249: =+I279 -> 0 | K249: =+J279 -> 0 | L249: =+K279 -> 0
A250: Einnahmen
B260: Geldverkehr
D261: Summe Einnahmen | E261: =SUM(E250:E260) -> 0 | F261: =SUM(F250:F260) -> 0 | G261: =SUM(G250:G260) -> 0 | H261: =SUM(H250:H260) -> 0 | I261: =SUM(I250:I260) -> 0 | J261: =SUM(J250:J260) -> 0 | K261: =SUM(K250:K260) -> 0 | L261: =SUM(L250:L260) -> 0
A262: Ausgaben
B276: Geldverkehr
D277: Summe Ausgaben | E277: =SUM(E263:E276) -> 0 | F277: =SUM(F263:F276) -> 0 | G277: =SUM(G263:G276) -> 0 | H277: =SUM(H263:H276) -> 0 | I277: =SUM(I263:I276) -> 0 | J277: =SUM(J263:J276) -> 0 | K277: =SUM(K263:K276) -> 0 | L277: =SUM(L263:L276) -> 0
D278: Saldo Einnahmen ./. Ausgaben | E278: =+E261-E277 -> 0 | F278: =+F261-F277 -> 0 | G278: =+G261-G277 -> 0 | H278: =+H261-H277 -> 0 | I278: =+I261-I277 -> 0 | J278: =+J261-J277 -> 0 | K278: =+K261-K277 -> 0 | L278: =+L261-L277 -> 0
...
